[{"county":"Kanawha","state_id":"WV"},{"county":"Berkeley","state_id":"WV"},{"county":"Monongalia","state_id":"WV"},{"county":"Cabell","state_id":"WV"},{"county":"Wood","state_id":"WV"},{"county":"Raleigh","state_id":"WV"},{"county":"Harrison","state_id":"WV"},{"county":"Mercer","state_id":"WV"},{"county":"Jefferson","state_id":"WV"},{"county":"Putnam","state_id":"WV"},{"county":"Marion","state_id":"WV"},{"county":"Ohio","state_id":"WV"},{"county":"Fayette","state_id":"WV"},{"county":"Wayne","state_id":"WV"},{"county":"Preston","state_id":"WV"},{"county":"Greenbrier","state_id":"WV"},{"county":"Logan","state_id":"WV"},{"county":"Marshall","state_id":"WV"},{"county":"Hancock","state_id":"WV"},{"county":"Randolph","state_id":"WV"},{"county":"Jackson","state_id":"WV"},{"county":"Mineral","state_id":"WV"},{"county":"Mason","state_id":"WV"},{"county":"Nicholas","state_id":"WV"},{"county":"Upshur","state_id":"WV"},{"county":"Mingo","state_id":"WV"},{"county":"Hampshire","state_id":"WV"},{"county":"Brooke","state_id":"WV"},{"county":"Boone","state_id":"WV"},{"county":"Wyoming","state_id":"WV"},{"county":"Lincoln","state_id":"WV"},{"county":"McDowell","state_id":"WV"},{"county":"Morgan","state_id":"WV"},{"county":"Lewis","state_id":"WV"},{"county":"Taylor","state_id":"WV"},{"county":"Barbour","state_id":"WV"},{"county":"Wetzel","state_id":"WV"},{"county":"Hardy","state_id":"WV"},{"county":"Roane","state_id":"WV"},{"county":"Braxton","state_id":"WV"},{"county":"Monroe","state_id":"WV"},{"county":"Summers","state_id":"WV"},{"county":"Grant","state_id":"WV"},{"county":"Ritchie","state_id":"WV"},{"county":"Webster","state_id":"WV"},{"county":"Tyler","state_id":"WV"},{"county":"Clay","state_id":"WV"},{"county":"Pocahontas","state_id":"WV"},{"county":"Doddridge","state_id":"WV"},{"county":"Pleasants","state_id":"WV"},{"county":"Gilmer","state_id":"WV"},{"county":"Tucker","state_id":"WV"},{"county":"Calhoun","state_id":"WV"},{"county":"Pendleton","state_id":"WV"},{"county":"Wirt","state_id":"WV"}]